gagada8234/__init__.py
gagada8234-2.1.7.dist-info/METADATA
gagada8234-2.1.7.dist-info/WHEEL
gagada8234-2.1.7.dist-info/top_level.txt
gagada8234-2.1.7.dist-info/RECORD
